pycopyql/__init__.py
pycopyql/args.py
pycopyql/cli.py
pycopyql/config.py
pycopyql/export.py
pycopyql/query.py
pycopyql/resolver/__init__.py
pycopyql/resolver/foreign_key.py
pycopyql/resolver/inflector.py
pycopyql/resolver/static.py
pycopyql-0.4.0.dist-info/METADATA
pycopyql-0.4.0.dist-info/RECORD
pycopyql-0.4.0.dist-info/WHEEL
pycopyql-0.4.0.dist-info/entry_points.txt
pycopyql-0.4.0.dist-info/top_level.txt
