Metadata-Version: 2.1
Name: pycopyql
Version: 0.4.0
Summary: Exports a subset of data from a relational database
Home-page: https://github.com/elazar/pycopyql
Author: Matthew Turland
Author-email: me@matthewturland.com
License: MIT
Keywords: database relational data export tool utility
Platform: UNKNOWN
Classifier: Development Status :: 3 - Alpha
Classifier: Environment :: Console
Classifier: Intended Audience :: Developers
Classifier: Programming Language :: Python :: 3 :: Only
Classifier: License :: OSI Approved :: MIT License
Classifier: Operating System :: OS Independent
Classifier: Topic :: Database
Classifier: Topic :: Utilities
Requires-Python: >=3.5
Requires-Dist: inflect (~=1.0.0)
Requires-Dist: SQLAlchemy (~=1.2.10)
